proof/__init__.py
proof/analysis.py
proof-0.4.1.dist-info/licenses/AUTHORS.rst
proof-0.4.1.dist-info/licenses/COPYING
proof-0.4.1.dist-info/METADATA
proof-0.4.1.dist-info/WHEEL
proof-0.4.1.dist-info/top_level.txt
proof-0.4.1.dist-info/RECORD
